YT_Searcher/__init__.py
YT_Searcher/yt_searcher.py
yt_searcher_for_py-0.0.2.dist-info/METADATA
yt_searcher_for_py-0.0.2.dist-info/WHEEL
yt_searcher_for_py-0.0.2.dist-info/top_level.txt
yt_searcher_for_py-0.0.2.dist-info/RECORD
